Metadata-Version: 2.1
Name: tfmpi2c
Version: 0.0.7
Summary: Corrected FRAME_5 constant from 0x0003 to 0x0005
Home-page: https://github.com/budryerson/TFMini-Plus_I2C_python
Author: Bud Ryerson
Author-email: bud@budryerson.com
License: UNKNOWN
Project-URL: Bug Tracker, https://github.com/budryerson/TFMini-Plus_I2C_python/issues
Platform: UNKNOWN
Classifier: Programming Language :: Python :: 3
Classifier: License :: OSI Approved :: MIT License
Classifier: Operating System :: OS Independent
Requires-Python: >=3.6
Requires-Dist: smbus
